vcd2df.py
vcd2df-1.0.dist-info/licenses/LICENSE
vcd2df-1.0.dist-info/WHEEL
vcd2df-1.0.dist-info/METADATA
vcd2df-1.0.dist-info/RECORD
