Metadata-Version: 2.4
Name: vcd2df
Version: 1.0
Summary: Value Change Dump to Data Frame (Pandas)
Author-email: Calvin Deutschbein <ckdeutschbein@willamette.edu>
License-Expression: GPL-3.0-or-later
License-File: LICENSE
Project-URL: Home, https://cd-public.github.io/
